kgp_configrendertoml/__init__.py
kgp_configrendertoml/configfile.py
kgp_configrendertoml/py.typed
kgp_configrendertoml-0.8.0.dist-info/METADATA
kgp_configrendertoml-0.8.0.dist-info/WHEEL
kgp_configrendertoml-0.8.0.dist-info/top_level.txt
kgp_configrendertoml-0.8.0.dist-info/RECORD
