Metadata-Version: 2.1
Name: kgp-configrendertoml
Version: 0.8.0
Summary: KubraGen Plugin: TOML config renderer
Home-page: https://github.com/RangelReale/kgp_configrendertoml
Author: Rangel Reale
Author-email: rangelreale@gmail.com
License: UNKNOWN
Platform: UNKNOWN
Classifier: Programming Language :: Python :: 3
Classifier: License :: OSI Approved :: MIT License
Classifier: Operating System :: OS Independent
Requires-Python: >=3.6
Requires-Dist: kubragen (>=0.8.2)
Requires-Dist: toml (>=0.10.2)
